sbp_env/__entry_point.py
sbp_env/__init__.py
sbp_env/_version.py
sbp_env/collisionChecker.py
sbp_env/engine.py
sbp_env/env.py
sbp_env/randomness.py
sbp_env/visualiser.py
sbp_env/planners/__init__.py
sbp_env/planners/basePlanner.py
sbp_env/planners/birrtPlanner.py
sbp_env/planners/informedrrtPlanner.py
sbp_env/planners/likelihoodPlanner.py
sbp_env/planners/mousePlanner.py
sbp_env/planners/nearbyPlanner.py
sbp_env/planners/prmPlanner.py
sbp_env/planners/rrdtPlanner.py
sbp_env/planners/rrtPlanner.py
sbp_env/samplers/__init__.py
sbp_env/samplers/baseSampler.py
sbp_env/samplers/birrtSampler.py
sbp_env/samplers/informedSampler.py
sbp_env/samplers/likelihoodPolicySampler.py
sbp_env/samplers/mouseSampler.py
sbp_env/samplers/nearbyPolicySampler.py
sbp_env/samplers/prmSampler.py
sbp_env/samplers/randomPolicySampler.py
sbp_env/utils/__init__.py
sbp_env/utils/common.py
sbp_env/utils/csv_stats_logger.py
sbp_env/utils/planner_registry.py
sbp_env-2.0.2.dist-info/LICENSE
sbp_env-2.0.2.dist-info/METADATA
sbp_env-2.0.2.dist-info/WHEEL
sbp_env-2.0.2.dist-info/entry_points.txt
sbp_env-2.0.2.dist-info/top_level.txt
sbp_env-2.0.2.dist-info/RECORD
