Metadata-Version: 2.1
Name: sbp-env
Version: 2.0.2
Summary: Motion planning environment for Sampling-based Planners
Home-page: https://github.com/soraxas/sbp-env
Author: Tin Lai (@soraxas)
Author-email: oscar@tinyiu.com
License: MIT
Keywords: motion planning robotics sbp rrt
Platform: UNKNOWN
Classifier: Environment :: Console
Classifier: Framework :: Matplotlib
Classifier: Intended Audience :: Developers
Classifier: Intended Audience :: End Users/Desktop
Classifier: Intended Audience :: System Administrators
Classifier: License :: OSI Approved :: MIT License
Classifier: Operating System :: MacOS
Classifier: Operating System :: POSIX
Classifier: Operating System :: Unix
Classifier: Programming Language :: Python :: 3.7
Classifier: Programming Language :: Python :: 3.8
Classifier: Programming Language :: Python :: 3.9
Classifier: Programming Language :: Python :: 3.10
Classifier: Topic :: Desktop Environment
Classifier: Topic :: Terminals
Classifier: Topic :: Utilities
Requires-Python: >=3.7
License-File: LICENSE
Requires-Dist: docopt (~=0.6.2)
Requires-Dist: pygame (~=2.0.1)
Requires-Dist: overrides (~=3.1.0)
Requires-Dist: SALib (~=1.3.12)
Requires-Dist: networkx (~=2.5)
Requires-Dist: pillow
Requires-Dist: tqdm (~=4.56.0)
Requires-Dist: rtree (>=0.9.4)
